{
	"$schema": "http://schema.management.azure.com/schemas/2015-01-01/deploymentTemplate.json#",
	"contentVersion": "1.0.0.0",
	"parameters": {
		"factoryName": {
			"type": "string",
			"metadata": "Data Factory name",
			"defaultValue": "azuredataFactorylearn1"
		},
		"Oraclelinkedservice_connectionString": {
			"type": "secureString",
			"metadata": "Secure string for 'connectionString' of 'Oraclelinkedservice'"
		}
	},
	"variables": {
		"factoryId": "[concat('Microsoft.DataFactory/factories/', parameters('factoryName'))]"
	},
	"resources": [
		{
			"name": "[concat(parameters('factoryName'), '/adlsparamdataset')]",
			"type": "Microsoft.DataFactory/factories/datasets",
			"apiVersion": "2018-06-01",
			"properties": {
				"linkedServiceName": {
					"referenceName": "Paramadlslinkedservice",
					"type": "LinkedServiceReference",
					"parameters": {
						"url": {
							"value": "@dataset().url",
							"type": "Expression"
						}
					}
				},
				"parameters": {
					"container_name": {
						"type": "string"
					},
					"parent_name": {
						"type": "string"
					},
					"file_name": {
						"type": "string"
					},
					"url": {
						"type": "string"
					}
				},
				"annotations": [],
				"type": "DelimitedText",
				"typeProperties": {
					"location": {
						"type": "AzureBlobFSLocation",
						"fileName": {
							"value": "@dataset().file_name",
							"type": "Expression"
						},
						"folderPath": {
							"value": "@dataset().parent_name",
							"type": "Expression"
						},
						"fileSystem": {
							"value": "@dataset().container_name",
							"type": "Expression"
						}
					},
					"columnDelimiter": ",",
					"escapeChar": "\\",
					"firstRowAsHeader": true,
					"quoteChar": "\""
				},
				"schema": []
			},
			"dependsOn": []
		},
		{
			"name": "[concat(parameters('factoryName'), '/adlstoblbmeta')]",
			"type": "Microsoft.DataFactory/factories/datasets",
			"apiVersion": "2018-06-01",
			"properties": {
				"linkedServiceName": {
					"referenceName": "AzureDataLakeStorage1",
					"type": "LinkedServiceReference"
				},
				"parameters": {
					"filename": {
						"type": "string"
					}
				},
				"annotations": [],
				"type": "DelimitedText",
				"typeProperties": {
					"location": {
						"type": "AzureBlobFSLocation",
						"fileName": {
							"value": "@dataset().filename",
							"type": "Expression"
						},
						"folderPath": "extrernalsinkdirectory",
						"fileSystem": "adlscontainer1"
					},
					"columnDelimiter": ",",
					"escapeChar": "\\",
					"firstRowAsHeader": true,
					"quoteChar": "\""
				},
				"schema": []
			},
			"dependsOn": []
		},
		{
			"name": "[concat(parameters('factoryName'), '/azureadlsdatatable')]",
			"type": "Microsoft.DataFactory/factories/datasets",
			"apiVersion": "2018-06-01",
			"properties": {
				"linkedServiceName": {
					"referenceName": "AzureDataLakeStorage1",
					"type": "LinkedServiceReference"
				},
				"annotations": [],
				"type": "DelimitedText",
				"typeProperties": {
					"location": {
						"type": "AzureBlobFSLocation",
						"fileName": "wrong.csv",
						"folderPath": "copydatapipeline1",
						"fileSystem": "adlscontainer1"
					},
					"columnDelimiter": ",",
					"escapeChar": "\\",
					"firstRowAsHeader": true,
					"quoteChar": "\""
				},
				"schema": [
					{
						"name": "Username; Identifier;One-time password;Recovery code;First name;Last name;Department;Location",
						"type": "String"
					}
				]
			},
			"dependsOn": []
		},
		{
			"name": "[concat(parameters('factoryName'), '/azuresourceparam')]",
			"type": "Microsoft.DataFactory/factories/datasets",
			"apiVersion": "2018-06-01",
			"properties": {
				"linkedServiceName": {
					"referenceName": "AzureDataLakeStorage1",
					"type": "LinkedServiceReference"
				},
				"parameters": {
					"folder": {
						"type": "string"
					}
				},
				"annotations": [],
				"type": "DelimitedText",
				"typeProperties": {
					"location": {
						"type": "AzureBlobFSLocation",
						"folderPath": {
							"value": "@dataset().folder",
							"type": "Expression"
						},
						"fileSystem": "adlscontainer1"
					},
					"columnDelimiter": ",",
					"escapeChar": "\\",
					"firstRowAsHeader": true,
					"quoteChar": "\""
				},
				"schema": []
			},
			"dependsOn": []
		},
		{
			"name": "[concat(parameters('factoryName'), '/blbdataset')]",
			"type": "Microsoft.DataFactory/factories/datasets",
			"apiVersion": "2018-06-01",
			"properties": {
				"linkedServiceName": {
					"referenceName": "AzureBlobStorage1",
					"type": "LinkedServiceReference"
				},
				"annotations": [],
				"type": "DelimitedText",
				"typeProperties": {
					"location": {
						"type": "AzureBlobStorageLocation",
						"fileName": "sample4.csv",
						"folderPath": "blbdirectory1",
						"container": "blbcontainer1"
					},
					"columnDelimiter": ",",
					"escapeChar": "\\",
					"firstRowAsHeader": true,
					"quoteChar": "\""
				},
				"schema": [
					{
						"name": "138126",
						"type": "String"
					},
					{
						"name": "T/T ADVANCE NET 30",
						"type": "String"
					},
					{
						"name": "HSINCHE",
						"type": "String"
					},
					{
						"name": "Sanmina-SCI Corp (Cons) 356",
						"type": "String"
					}
				]
			},
			"dependsOn": []
		},
		{
			"name": "[concat(parameters('factoryName'), '/blbfilefolderparam')]",
			"type": "Microsoft.DataFactory/factories/datasets",
			"apiVersion": "2018-06-01",
			"properties": {
				"linkedServiceName": {
					"referenceName": "AzureBlobStorage1",
					"type": "LinkedServiceReference"
				},
				"parameters": {
					"folder": {
						"type": "string"
					},
					"file": {
						"type": "string"
					}
				},
				"annotations": [],
				"type": "DelimitedText",
				"typeProperties": {
					"location": {
						"type": "AzureBlobStorageLocation",
						"fileName": {
							"value": "@dataset().file",
							"type": "Expression"
						},
						"folderPath": {
							"value": "@dataset().folder",
							"type": "Expression"
						},
						"container": "blbcontainer1"
					},
					"columnDelimiter": ",",
					"escapeChar": "\\",
					"firstRowAsHeader": true,
					"quoteChar": "\""
				},
				"schema": []
			},
			"dependsOn": []
		},
		{
			"name": "[concat(parameters('factoryName'), '/blbmeta')]",
			"type": "Microsoft.DataFactory/factories/datasets",
			"apiVersion": "2018-06-01",
			"properties": {
				"linkedServiceName": {
					"referenceName": "AzureBlobStorage1",
					"type": "LinkedServiceReference"
				},
				"parameters": {
					"destfilename": {
						"type": "string"
					}
				},
				"annotations": [],
				"type": "DelimitedText",
				"typeProperties": {
					"location": {
						"type": "AzureBlobStorageLocation",
						"fileName": {
							"value": "@dataset().destfilename",
							"type": "Expression"
						},
						"folderPath": {
							"value": "@formatDateTime(utcNow(),'yyyy-MM-dd')",
							"type": "Expression"
						},
						"container": "blbcontainer1"
					},
					"columnDelimiter": ",",
					"escapeChar": "\\",
					"firstRowAsHeader": true,
					"quoteChar": "\""
				},
				"schema": []
			},
			"dependsOn": []
		},
		{
			"name": "[concat(parameters('factoryName'), '/blbparam')]",
			"type": "Microsoft.DataFactory/factories/datasets",
			"apiVersion": "2018-06-01",
			"properties": {
				"linkedServiceName": {
					"referenceName": "AzureBlobStorage1",
					"type": "LinkedServiceReference"
				},
				"parameters": {
					"folder": {
						"type": "string"
					}
				},
				"annotations": [],
				"type": "DelimitedText",
				"typeProperties": {
					"location": {
						"type": "AzureBlobStorageLocation",
						"folderPath": {
							"value": "@dataset().folder",
							"type": "Expression"
						},
						"container": "blbcontainer1"
					},
					"columnDelimiter": ",",
					"escapeChar": "\\",
					"firstRowAsHeader": true,
					"quoteChar": "\""
				},
				"schema": []
			},
			"dependsOn": []
		},
		{
			"name": "[concat(parameters('factoryName'), '/updatedempdetails')]",
			"type": "Microsoft.DataFactory/factories/datasets",
			"apiVersion": "2018-06-01",
			"properties": {
				"linkedServiceName": {
					"referenceName": "AzureDataLakeStorage1",
					"type": "LinkedServiceReference"
				},
				"annotations": [],
				"type": "DelimitedText",
				"typeProperties": {
					"location": {
						"type": "AzureBlobFSLocation",
						"fileName": "emp_update.csv",
						"folderPath": "extrernalsinkdirectory",
						"fileSystem": "adlscontainer1"
					},
					"columnDelimiter": ",",
					"escapeChar": "\\",
					"firstRowAsHeader": true,
					"quoteChar": "\""
				},
				"schema": [
					{
						"name": "EMPLOYEE_ID",
						"type": "String"
					},
					{
						"name": "FIRST_NAME",
						"type": "String"
					},
					{
						"name": "LAST_NAME",
						"type": "String"
					},
					{
						"name": "EMAIL",
						"type": "String"
					},
					{
						"name": "PHONE_NUMBER",
						"type": "String"
					},
					{
						"name": "HIRE_DATE",
						"type": "String"
					},
					{
						"name": "JOB_ID",
						"type": "String"
					},
					{
						"name": "SALARY",
						"type": "String"
					},
					{
						"name": "COMMISSION_PCT",
						"type": "String"
					},
					{
						"name": "MANAGER_ID",
						"type": "String"
					},
					{
						"name": "DEPARTMENT_ID",
						"type": "String"
					}
				]
			},
			"dependsOn": []
		},
		{
			"name": "[concat(parameters('factoryName'), '/Oraclelinkedservice')]",
			"type": "Microsoft.DataFactory/factories/linkedServices",
			"apiVersion": "2018-06-01",
			"properties": {
				"annotations": [],
				"type": "Oracle",
				"typeProperties": {
					"connectionString": "[parameters('Oraclelinkedservice_connectionString')]"
				},
				"connectVia": {
					"referenceName": "localdb",
					"type": "IntegrationRuntimeReference"
				}
			},
			"dependsOn": []
		},
		{
			"name": "[concat(parameters('factoryName'), '/blbfileaddnotifylogicappwithscheduletrig')]",
			"type": "Microsoft.DataFactory/factories/pipelines",
			"apiVersion": "2018-06-01",
			"properties": {
				"activities": [
					{
						"name": "Copy data1",
						"type": "Copy",
						"dependsOn": [],
						"policy": {
							"timeout": "0.12:00:00",
							"retry": 0,
							"retryIntervalInSeconds": 30,
							"secureOutput": false,
							"secureInput": false
						},
						"userProperties": [],
						"typeProperties": {
							"source": {
								"type": "DelimitedTextSource",
								"storeSettings": {
									"type": "AzureBlobFSReadSettings",
									"recursive": true,
									"enablePartitionDiscovery": false
								},
								"formatSettings": {
									"type": "DelimitedTextReadSettings"
								}
							},
							"sink": {
								"type": "DelimitedTextSink",
								"storeSettings": {
									"type": "AzureBlobStorageWriteSettings"
								},
								"formatSettings": {
									"type": "DelimitedTextWriteSettings",
									"quoteAllText": true,
									"fileExtension": ".txt"
								}
							},
							"enableStaging": false,
							"translator": {
								"type": "TabularTranslator",
								"typeConversion": true,
								"typeConversionSettings": {
									"allowDataTruncation": true,
									"treatBooleanAsNumber": false
								}
							}
						},
						"inputs": [
							{
								"referenceName": "adlsmetadata",
								"type": "DatasetReference",
								"parameters": {}
							}
						],
						"outputs": [
							{
								"referenceName": "blbdataset",
								"type": "DatasetReference",
								"parameters": {}
							}
						]
					}
				],
				"policy": {
					"elapsedTimeMetric": {}
				},
				"annotations": [],
				"lastPublishTime": "2025-02-15T13:04:22Z"
			},
			"dependsOn": [
				"[concat(variables('factoryId'), '/datasets/blbdataset')]"
			]
		},
		{
			"name": "[concat(parameters('factoryName'), '/logicapppipeline1')]",
			"type": "Microsoft.DataFactory/factories/pipelines",
			"apiVersion": "2018-06-01",
			"properties": {
				"activities": [
					{
						"name": "Audit_success_activity",
						"type": "SqlServerStoredProcedure",
						"dependsOn": [
							{
								"activity": "Copy data1",
								"dependencyConditions": [
									"Succeeded"
								]
							}
						],
						"policy": {
							"timeout": "0.12:00:00",
							"retry": 0,
							"retryIntervalInSeconds": 30,
							"secureOutput": false,
							"secureInput": false
						},
						"userProperties": [],
						"typeProperties": {
							"storedProcedureName": "[[dbo].[sp_InsertPipelineRunDetails]",
							"storedProcedureParameters": {
								"DataFactoryName": {
									"value": {
										"value": "@pipeline().DataFactory",
										"type": "Expression"
									},
									"type": "String"
								},
								"PipelineName": {
									"value": {
										"value": "@pipeline().Pipeline",
										"type": "Expression"
									},
									"type": "String"
								},
								"PipelineRunID": {
									"value": {
										"value": "@pipeline().RunId",
										"type": "Expression"
									},
									"type": "String"
								},
								"Source_tab_Count": {
									"value": {
										"value": "@activity('Copy data1').output.dataRead",
										"type": "Expression"
									},
									"type": "Int32"
								},
								"Status": {
									"value": "succeed",
									"type": "String"
								},
								"Target_tab_Count": {
									"value": {
										"value": "@activity('Copy data1').output.dataWritten",
										"type": "Expression"
									},
									"type": "Int32"
								},
								"TriggerName": {
									"value": {
										"value": "@pipeline().TriggerName",
										"type": "Expression"
									},
									"type": "String"
								},
								"TriggerRunID": {
									"value": {
										"value": "@pipeline().TriggerId",
										"type": "Expression"
									},
									"type": "String"
								},
								"TriggerRunTime": {
									"value": {
										"value": "@pipeline().TriggerTime",
										"type": "Expression"
									},
									"type": "String"
								},
								"TriggerType": {
									"value": {
										"value": "@pipeline().TriggerType",
										"type": "Expression"
									},
									"type": "String"
								}
							}
						},
						"linkedServiceName": {
							"referenceName": "Sqlserverdataadls",
							"type": "LinkedServiceReference"
						}
					},
					{
						"name": "Copy data1",
						"type": "Copy",
						"dependsOn": [],
						"policy": {
							"timeout": "0.12:00:00",
							"retry": 0,
							"retryIntervalInSeconds": 30,
							"secureOutput": false,
							"secureInput": false
						},
						"userProperties": [],
						"typeProperties": {
							"source": {
								"type": "DelimitedTextSource",
								"storeSettings": {
									"type": "AzureBlobFSReadSettings",
									"recursive": true,
									"enablePartitionDiscovery": false
								},
								"formatSettings": {
									"type": "DelimitedTextReadSettings"
								}
							},
							"sink": {
								"type": "DelimitedTextSink",
								"storeSettings": {
									"type": "AzureBlobStorageWriteSettings"
								},
								"formatSettings": {
									"type": "DelimitedTextWriteSettings",
									"quoteAllText": true,
									"fileExtension": ".txt"
								}
							},
							"enableStaging": false,
							"translator": {
								"type": "TabularTranslator",
								"typeConversion": true,
								"typeConversionSettings": {
									"allowDataTruncation": true,
									"treatBooleanAsNumber": false
								}
							}
						},
						"inputs": [
							{
								"referenceName": "azureadlsdatatable",
								"type": "DatasetReference",
								"parameters": {}
							}
						],
						"outputs": [
							{
								"referenceName": "blbdataset",
								"type": "DatasetReference",
								"parameters": {}
							}
						]
					},
					{
						"name": "Audit_failed_activity",
						"type": "SqlServerStoredProcedure",
						"dependsOn": [
							{
								"activity": "Copy data1",
								"dependencyConditions": [
									"Failed"
								]
							}
						],
						"policy": {
							"timeout": "0.12:00:00",
							"retry": 0,
							"retryIntervalInSeconds": 30,
							"secureOutput": false,
							"secureInput": false
						},
						"userProperties": [],
						"typeProperties": {
							"storedProcedureName": "[[dbo].[sp_InsertPipelineRunDetails]",
							"storedProcedureParameters": {
								"DataFactoryName": {
									"value": {
										"value": "@pipeline().DataFactory",
										"type": "Expression"
									},
									"type": "String"
								},
								"PipelineName": {
									"value": {
										"value": "@pipeline().Pipeline",
										"type": "Expression"
									},
									"type": "String"
								},
								"PipelineRunID": {
									"value": {
										"value": "@pipeline().RunId",
										"type": "Expression"
									},
									"type": "String"
								},
								"Source_tab_Count": {
									"value": null,
									"type": "Int32"
								},
								"Status": {
									"value": "failed",
									"type": "String"
								},
								"Target_tab_Count": {
									"value": null,
									"type": "Int32"
								},
								"TriggerName": {
									"value": {
										"value": "@pipeline().TriggerName",
										"type": "Expression"
									},
									"type": "String"
								},
								"TriggerRunID": {
									"value": {
										"value": "@pipeline().TriggerId",
										"type": "Expression"
									},
									"type": "String"
								},
								"TriggerRunTime": {
									"value": {
										"value": "@pipeline().TriggerTime",
										"type": "Expression"
									},
									"type": "String"
								},
								"TriggerType": {
									"value": {
										"value": "@pipeline().TriggerType",
										"type": "Expression"
									},
									"type": "String"
								}
							}
						},
						"linkedServiceName": {
							"referenceName": "Sqlserverdataadls",
							"type": "LinkedServiceReference"
						}
					},
					{
						"name": "Web1",
						"type": "WebActivity",
						"dependsOn": [
							{
								"activity": "Audit_failed_activity",
								"dependencyConditions": [
									"Succeeded"
								]
							}
						],
						"policy": {
							"timeout": "0.12:00:00",
							"retry": 0,
							"retryIntervalInSeconds": 30,
							"secureOutput": false,
							"secureInput": false
						},
						"userProperties": [],
						"typeProperties": {
							"method": "POST",
							"headers": {},
							"url": {
								"value": "https://prod-09.centralindia.logic.azure.com:443/workflows/79d4a2cc2ec44f51a5f6984d21abacb7/triggers/When_a_HTTP_request_is_received/paths/invoke?api-version=2016-10-01&sp=%2Ftriggers%2FWhen_a_HTTP_request_is_received%2Frun&sv=1.0&sig=yBpetvjEt1N9_F6pZv7Ub3CeratfmPfXYmB8rQtCFIQ",
								"type": "Expression"
							},
							"body": {
								"value": "{\n    \"message\":\"Audit_failed_activity\"\n}",
								"type": "Expression"
							}
						}
					}
				],
				"policy": {
					"elapsedTimeMetric": {}
				},
				"annotations": [],
				"lastPublishTime": "2025-02-17T13:13:51Z"
			},
			"dependsOn": [
				"[concat(variables('factoryId'), '/datasets/azureadlsdatatable')]",
				"[concat(variables('factoryId'), '/datasets/blbdataset')]"
			]
		},
		{
			"name": "[concat(parameters('factoryName'), '/logicwithprocedurepiprline')]",
			"type": "Microsoft.DataFactory/factories/pipelines",
			"apiVersion": "2018-06-01",
			"properties": {
				"activities": [
					{
						"name": "Copy data1",
						"type": "Copy",
						"dependsOn": [],
						"policy": {
							"timeout": "0.12:00:00",
							"retry": 0,
							"retryIntervalInSeconds": 30,
							"secureOutput": false,
							"secureInput": false
						},
						"userProperties": [],
						"typeProperties": {
							"source": {
								"type": "DelimitedTextSource",
								"storeSettings": {
									"type": "AzureBlobFSReadSettings",
									"recursive": true,
									"enablePartitionDiscovery": false
								},
								"formatSettings": {
									"type": "DelimitedTextReadSettings"
								}
							},
							"sink": {
								"type": "DelimitedTextSink",
								"storeSettings": {
									"type": "AzureBlobStorageWriteSettings"
								},
								"formatSettings": {
									"type": "DelimitedTextWriteSettings",
									"quoteAllText": true,
									"fileExtension": ".txt"
								}
							},
							"enableStaging": false,
							"translator": {
								"type": "TabularTranslator",
								"typeConversion": true,
								"typeConversionSettings": {
									"allowDataTruncation": true,
									"treatBooleanAsNumber": false
								}
							}
						},
						"inputs": [
							{
								"referenceName": "adlsmetadata",
								"type": "DatasetReference",
								"parameters": {}
							}
						],
						"outputs": [
							{
								"referenceName": "DelimitedText2",
								"type": "DatasetReference",
								"parameters": {}
							}
						]
					}
				],
				"policy": {
					"elapsedTimeMetric": {}
				},
				"annotations": [],
				"lastPublishTime": "2025-02-15T12:53:56Z"
			},
			"dependsOn": []
		},
		{
			"name": "[concat(parameters('factoryName'), '/metadata')]",
			"type": "Microsoft.DataFactory/factories/pipelines",
			"apiVersion": "2018-06-01",
			"properties": {
				"activities": [
					{
						"name": "metaactivitypractise",
						"type": "GetMetadata",
						"dependsOn": [],
						"policy": {
							"timeout": "0.12:00:00",
							"retry": 0,
							"retryIntervalInSeconds": 30,
							"secureOutput": false,
							"secureInput": false
						},
						"userProperties": [],
						"typeProperties": {
							"dataset": {
								"referenceName": "adlsmetadata",
								"type": "DatasetReference",
								"parameters": {}
							},
							"fieldList": [
								"childItems"
							],
							"storeSettings": {
								"type": "AzureBlobFSReadSettings",
								"recursive": true,
								"enablePartitionDiscovery": false
							},
							"formatSettings": {
								"type": "DelimitedTextReadSettings"
							}
						}
					},
					{
						"name": "Filter1",
						"type": "Filter",
						"dependsOn": [
							{
								"activity": "metaactivitypractise",
								"dependencyConditions": [
									"Succeeded"
								]
							}
						],
						"userProperties": [],
						"typeProperties": {
							"items": {
								"value": "@activity('metaactivitypractise').output.childItems",
								"type": "Expression"
							},
							"condition": {
								"value": "@equals(item().type,'File')",
								"type": "Expression"
							}
						}
					},
					{
						"name": "ForEach1",
						"type": "ForEach",
						"dependsOn": [
							{
								"activity": "Filter1",
								"dependencyConditions": [
									"Succeeded"
								]
							}
						],
						"userProperties": [],
						"typeProperties": {
							"items": {
								"value": "@activity('Filter1').output.Value",
								"type": "Expression"
							},
							"isSequential": true,
							"activities": [
								{
									"name": "Set variable1",
									"type": "SetVariable",
									"dependsOn": [],
									"policy": {
										"secureOutput": false,
										"secureInput": false
									},
									"userProperties": [],
									"typeProperties": {
										"variableName": "str",
										"value": {
											"value": "@item().name",
											"type": "Expression"
										}
									}
								},
								{
									"name": "Copy data1",
									"type": "Copy",
									"dependsOn": [
										{
											"activity": "Set variable1",
											"dependencyConditions": [
												"Succeeded"
											]
										}
									],
									"policy": {
										"timeout": "0.12:00:00",
										"retry": 0,
										"retryIntervalInSeconds": 30,
										"secureOutput": false,
										"secureInput": false
									},
									"userProperties": [],
									"typeProperties": {
										"source": {
											"type": "DelimitedTextSource",
											"storeSettings": {
												"type": "AzureBlobFSReadSettings",
												"recursive": true,
												"enablePartitionDiscovery": false
											},
											"formatSettings": {
												"type": "DelimitedTextReadSettings"
											}
										},
										"sink": {
											"type": "DelimitedTextSink",
											"storeSettings": {
												"type": "AzureBlobStorageWriteSettings"
											},
											"formatSettings": {
												"type": "DelimitedTextWriteSettings",
												"quoteAllText": true,
												"fileExtension": ".txt"
											}
										},
										"enableStaging": false,
										"translator": {
											"type": "TabularTranslator",
											"typeConversion": true,
											"typeConversionSettings": {
												"allowDataTruncation": true,
												"treatBooleanAsNumber": false
											}
										}
									},
									"inputs": [
										{
											"referenceName": "adlstoblbmeta",
											"type": "DatasetReference",
											"parameters": {
												"filename": {
													"value": "@item().value",
													"type": "Expression"
												}
											}
										}
									],
									"outputs": [
										{
											"referenceName": "blbmeta",
											"type": "DatasetReference",
											"parameters": {
												"destfilename": {
													"value": "@item().value",
													"type": "Expression"
												}
											}
										}
									]
								}
							]
						}
					}
				],
				"policy": {
					"elapsedTimeMetric": {}
				},
				"variables": {
					"str": {
						"type": "String"
					},
					"str1": {
						"type": "String"
					}
				},
				"annotations": [],
				"lastPublishTime": "2025-02-18T12:24:00Z"
			},
			"dependsOn": [
				"[concat(variables('factoryId'), '/datasets/adlstoblbmeta')]",
				"[concat(variables('factoryId'), '/datasets/blbmeta')]"
			]
		},
		{
			"name": "[concat(parameters('factoryName'), '/metadataadlstoblb')]",
			"type": "Microsoft.DataFactory/factories/pipelines",
			"apiVersion": "2018-06-01",
			"properties": {
				"activities": [
					{
						"name": "Get Metadata1",
						"type": "GetMetadata",
						"dependsOn": [],
						"policy": {
							"timeout": "0.12:00:00",
							"retry": 0,
							"retryIntervalInSeconds": 30,
							"secureOutput": false,
							"secureInput": false
						},
						"userProperties": [],
						"typeProperties": {
							"dataset": {
								"referenceName": "adlsmetadata",
								"type": "DatasetReference",
								"parameters": {}
							},
							"fieldList": [
								"childItems"
							],
							"storeSettings": {
								"type": "AzureBlobFSReadSettings",
								"recursive": true,
								"enablePartitionDiscovery": false
							},
							"formatSettings": {
								"type": "DelimitedTextReadSettings"
							}
						}
					},
					{
						"name": "Filter1",
						"type": "Filter",
						"dependsOn": [
							{
								"activity": "Get Metadata1",
								"dependencyConditions": [
									"Succeeded"
								]
							}
						],
						"userProperties": [],
						"typeProperties": {
							"items": {
								"value": "@activity('Get Metadata1').output.childItems",
								"type": "Expression"
							},
							"condition": {
								"value": "@equals(item().type,'File' )",
								"type": "Expression"
							}
						}
					},
					{
						"name": "ForEach1",
						"type": "ForEach",
						"dependsOn": [
							{
								"activity": "Filter1",
								"dependencyConditions": [
									"Succeeded"
								]
							}
						],
						"userProperties": [],
						"typeProperties": {
							"items": {
								"value": "@activity('Filter1').output.Value",
								"type": "Expression"
							},
							"isSequential": true,
							"activities": [
								{
									"name": "Set variable1",
									"type": "SetVariable",
									"dependsOn": [],
									"policy": {
										"secureOutput": false,
										"secureInput": false
									},
									"userProperties": [],
									"typeProperties": {
										"variableName": "str1",
										"value": {
											"value": "@item().name",
											"type": "Expression"
										}
									}
								},
								{
									"name": "Copy data1",
									"type": "Copy",
									"dependsOn": [
										{
											"activity": "Set variable1",
											"dependencyConditions": [
												"Succeeded"
											]
										}
									],
									"policy": {
										"timeout": "0.12:00:00",
										"retry": 0,
										"retryIntervalInSeconds": 30,
										"secureOutput": false,
										"secureInput": false
									},
									"userProperties": [],
									"typeProperties": {
										"source": {
											"type": "DelimitedTextSource",
											"storeSettings": {
												"type": "AzureBlobFSReadSettings",
												"recursive": true,
												"enablePartitionDiscovery": false
											},
											"formatSettings": {
												"type": "DelimitedTextReadSettings"
											}
										},
										"sink": {
											"type": "DelimitedTextSink",
											"storeSettings": {
												"type": "AzureBlobStorageWriteSettings"
											},
											"formatSettings": {
												"type": "DelimitedTextWriteSettings",
												"quoteAllText": true,
												"fileExtension": ".txt"
											}
										},
										"enableStaging": false,
										"translator": {
											"type": "TabularTranslator",
											"typeConversion": true,
											"typeConversionSettings": {
												"allowDataTruncation": true,
												"treatBooleanAsNumber": false
											}
										}
									},
									"inputs": [
										{
											"referenceName": "adlstoblbmeta",
											"type": "DatasetReference",
											"parameters": {
												"filename": {
													"value": "@item().name",
													"type": "Expression"
												}
											}
										}
									],
									"outputs": [
										{
											"referenceName": "blbmeta",
											"type": "DatasetReference",
											"parameters": {
												"destfilename": {
													"value": "@item().name",
													"type": "Expression"
												}
											}
										}
									]
								}
							]
						}
					}
				],
				"policy": {
					"elapsedTimeMetric": {}
				},
				"variables": {
					"str1": {
						"type": "String"
					}
				},
				"annotations": [],
				"lastPublishTime": "2025-02-18T12:24:00Z"
			},
			"dependsOn": [
				"[concat(variables('factoryId'), '/datasets/adlstoblbmeta')]",
				"[concat(variables('factoryId'), '/datasets/blbmeta')]"
			]
		},
		{
			"name": "[concat(parameters('factoryName'), '/metadataforecah')]",
			"type": "Microsoft.DataFactory/factories/pipelines",
			"apiVersion": "2018-06-01",
			"properties": {
				"activities": [
					{
						"name": "Get Metadata1",
						"type": "GetMetadata",
						"dependsOn": [],
						"policy": {
							"timeout": "0.12:00:00",
							"retry": 0,
							"retryIntervalInSeconds": 30,
							"secureOutput": false,
							"secureInput": false
						},
						"userProperties": [],
						"typeProperties": {
							"dataset": {
								"referenceName": "adlsmetadata",
								"type": "DatasetReference",
								"parameters": {}
							},
							"fieldList": [
								"childItems"
							],
							"storeSettings": {
								"type": "AzureBlobFSReadSettings",
								"recursive": true,
								"enablePartitionDiscovery": false
							},
							"formatSettings": {
								"type": "DelimitedTextReadSettings"
							}
						}
					},
					{
						"name": "ForEach1",
						"type": "ForEach",
						"dependsOn": [
							{
								"activity": "Get Metadata1",
								"dependencyConditions": [
									"Succeeded"
								]
							}
						],
						"userProperties": [],
						"typeProperties": {
							"items": {
								"value": "@activity('Get Metadata1').output.childItems",
								"type": "Expression"
							},
							"isSequential": true,
							"activities": [
								{
									"name": "Set variable1",
									"type": "SetVariable",
									"dependsOn": [],
									"policy": {
										"secureOutput": false,
										"secureInput": false
									},
									"userProperties": [],
									"typeProperties": {
										"variableName": "value",
										"value": {
											"value": "@array(item())",
											"type": "Expression"
										}
									}
								},
								{
									"name": "Filter1",
									"type": "Filter",
									"dependsOn": [
										{
											"activity": "Set variable1",
											"dependencyConditions": [
												"Succeeded"
											]
										}
									],
									"userProperties": [],
									"typeProperties": {
										"items": {
											"value": "@array(item())",
											"type": "Expression"
										},
										"condition": {
											"value": "@equals(item().type,'File' )",
											"type": "Expression"
										}
									}
								}
							]
						}
					}
				],
				"policy": {
					"elapsedTimeMetric": {}
				},
				"variables": {
					"value": {
						"type": "Array"
					},
					"x": {
						"type": "String"
					}
				},
				"annotations": [],
				"lastPublishTime": "2025-02-06T05:15:09Z"
			},
			"dependsOn": []
		},
		{
			"name": "[concat(parameters('factoryName'), '/metadatatablepipeline')]",
			"type": "Microsoft.DataFactory/factories/pipelines",
			"apiVersion": "2018-06-01",
			"properties": {
				"activities": [
					{
						"name": "Get Metadata1",
						"type": "GetMetadata",
						"dependsOn": [],
						"policy": {
							"timeout": "0.12:00:00",
							"retry": 0,
							"retryIntervalInSeconds": 30,
							"secureOutput": false,
							"secureInput": false
						},
						"userProperties": [],
						"typeProperties": {
							"dataset": {
								"referenceName": "adlsmetadata",
								"type": "DatasetReference",
								"parameters": {}
							},
							"fieldList": [
								"childItems"
							],
							"storeSettings": {
								"type": "AzureBlobFSReadSettings",
								"recursive": true,
								"enablePartitionDiscovery": false
							},
							"formatSettings": {
								"type": "DelimitedTextReadSettings"
							}
						}
					},
					{
						"name": "Filter1",
						"type": "Filter",
						"dependsOn": [
							{
								"activity": "Get Metadata1",
								"dependencyConditions": [
									"Succeeded"
								]
							}
						],
						"userProperties": [],
						"typeProperties": {
							"items": {
								"value": "@activity('Get Metadata1').output.childItems",
								"type": "Expression"
							},
							"condition": {
								"value": "@equals(item().type,'File')",
								"type": "Expression"
							}
						}
					},
					{
						"name": "ForEach1",
						"type": "ForEach",
						"dependsOn": [
							{
								"activity": "Filter1",
								"dependencyConditions": [
									"Succeeded"
								]
							}
						],
						"userProperties": [],
						"typeProperties": {
							"items": {
								"value": "@activity('Filter1').output.Value",
								"type": "Expression"
							},
							"isSequential": true,
							"activities": [
								{
									"name": "Set variable1",
									"type": "SetVariable",
									"dependsOn": [],
									"policy": {
										"secureOutput": false,
										"secureInput": false
									},
									"userProperties": [],
									"typeProperties": {
										"variableName": "str1",
										"value": {
											"value": "@item().name",
											"type": "Expression"
										}
									}
								},
								{
									"name": "Copy data1",
									"type": "Copy",
									"dependsOn": [
										{
											"activity": "Set variable1",
											"dependencyConditions": [
												"Succeeded"
											]
										}
									],
									"policy": {
										"timeout": "0.12:00:00",
										"retry": 0,
										"retryIntervalInSeconds": 30,
										"secureOutput": false,
										"secureInput": false
									},
									"userProperties": [],
									"typeProperties": {
										"source": {
											"type": "DelimitedTextSource",
											"storeSettings": {
												"type": "AzureBlobFSReadSettings",
												"recursive": true,
												"enablePartitionDiscovery": false
											},
											"formatSettings": {
												"type": "DelimitedTextReadSettings"
											}
										},
										"sink": {
											"type": "AzureSqlSink",
											"writeBehavior": "insert",
											"sqlWriterUseTableLock": false,
											"tableOption": "autoCreate",
											"disableMetricsCollection": false
										},
										"enableStaging": false,
										"translator": {
											"type": "TabularTranslator",
											"typeConversion": true,
											"typeConversionSettings": {
												"allowDataTruncation": true,
												"treatBooleanAsNumber": false
											}
										}
									},
									"inputs": [
										{
											"referenceName": "adlstoblbmeta",
											"type": "DatasetReference",
											"parameters": {
												"filename": {
													"value": "@item().name",
													"type": "Expression"
												}
											}
										}
									],
									"outputs": [
										{
											"referenceName": "AzureSqlTable3",
											"type": "DatasetReference",
											"parameters": {
												"tabletest": {
													"value": "@replace(item().name,'.csv','')",
													"type": "Expression"
												}
											}
										}
									]
								}
							]
						}
					}
				],
				"policy": {
					"elapsedTimeMetric": {}
				},
				"variables": {
					"str1": {
						"type": "String"
					}
				},
				"annotations": [],
				"lastPublishTime": "2025-02-18T12:24:00Z"
			},
			"dependsOn": [
				"[concat(variables('factoryId'), '/datasets/adlstoblbmeta')]"
			]
		},
		{
			"name": "[concat(parameters('factoryName'), '/pipeline1')]",
			"type": "Microsoft.DataFactory/factories/pipelines",
			"apiVersion": "2018-06-01",
			"properties": {
				"activities": [
					{
						"name": "Copy data1",
						"type": "Copy",
						"dependsOn": [],
						"policy": {
							"timeout": "0.12:00:00",
							"retry": 0,
							"retryIntervalInSeconds": 30,
							"secureOutput": false,
							"secureInput": false
						},
						"userProperties": [],
						"typeProperties": {
							"source": {
								"type": "DelimitedTextSource",
								"storeSettings": {
									"type": "AzureBlobStorageReadSettings",
									"recursive": true,
									"enablePartitionDiscovery": false
								},
								"formatSettings": {
									"type": "DelimitedTextReadSettings"
								}
							},
							"sink": {
								"type": "AzureSqlSink",
								"writeBehavior": "insert",
								"sqlWriterUseTableLock": false,
								"tableOption": "autoCreate",
								"disableMetricsCollection": false
							},
							"enableStaging": false,
							"translator": {
								"type": "TabularTranslator",
								"typeConversion": true,
								"typeConversionSettings": {
									"allowDataTruncation": true,
									"treatBooleanAsNumber": false
								}
							}
						},
						"inputs": [
							{
								"referenceName": "blbdataset",
								"type": "DatasetReference",
								"parameters": {}
							}
						],
						"outputs": [
							{
								"referenceName": "AzureSqlTable1",
								"type": "DatasetReference",
								"parameters": {}
							}
						]
					}
				],
				"policy": {
					"elapsedTimeMetric": {}
				},
				"annotations": [],
				"lastPublishTime": "2025-02-05T02:40:00Z"
			},
			"dependsOn": [
				"[concat(variables('factoryId'), '/datasets/blbdataset')]"
			]
		},
		{
			"name": "[concat(parameters('factoryName'), '/pipeline2')]",
			"type": "Microsoft.DataFactory/factories/pipelines",
			"apiVersion": "2018-06-01",
			"properties": {
				"activities": [
					{
						"name": "Copy data1",
						"type": "Copy",
						"dependsOn": [],
						"policy": {
							"timeout": "0.12:00:00",
							"retry": 0,
							"retryIntervalInSeconds": 30,
							"secureOutput": false,
							"secureInput": false
						},
						"userProperties": [],
						"typeProperties": {
							"source": {
								"type": "DelimitedTextSource",
								"storeSettings": {
									"type": "AzureBlobFSReadSettings",
									"recursive": true,
									"enablePartitionDiscovery": false
								},
								"formatSettings": {
									"type": "DelimitedTextReadSettings"
								}
							},
							"sink": {
								"type": "DelimitedTextSink",
								"storeSettings": {
									"type": "AzureBlobFSWriteSettings"
								},
								"formatSettings": {
									"type": "DelimitedTextWriteSettings",
									"quoteAllText": true,
									"fileExtension": ".txt"
								}
							},
							"enableStaging": false,
							"translator": {
								"type": "TabularTranslator",
								"typeConversion": true,
								"typeConversionSettings": {
									"allowDataTruncation": true,
									"treatBooleanAsNumber": false
								}
							}
						},
						"inputs": [
							{
								"referenceName": "adlsparamdataset",
								"type": "DatasetReference",
								"parameters": {
									"container_name": {
										"value": "@pipeline().parameters.sourcecontainer",
										"type": "Expression"
									},
									"parent_name": {
										"value": "@pipeline().parameters.sourcedirectory",
										"type": "Expression"
									},
									"file_name": {
										"value": "@pipeline().parameters.sourcefile",
										"type": "Expression"
									},
									"url": {
										"value": "@pipeline().globalParameters.adlsglobalparam",
										"type": "Expression"
									}
								}
							}
						],
						"outputs": [
							{
								"referenceName": "adlsparamdataset",
								"type": "DatasetReference",
								"parameters": {
									"container_name": {
										"value": "@pipeline().parameters.sinkcontainer",
										"type": "Expression"
									},
									"parent_name": {
										"value": "@pipeline().parameters.sinkdirectory",
										"type": "Expression"
									},
									"file_name": {
										"value": "@pipeline().parameters.sinkfile",
										"type": "Expression"
									},
									"url": {
										"value": "@pipeline().globalParameters.adlsglobalparam2",
										"type": "Expression"
									}
								}
							}
						]
					}
				],
				"policy": {
					"elapsedTimeMetric": {}
				},
				"parameters": {
					"sourcecontainer": {
						"type": "string"
					},
					"sourcedirectory": {
						"type": "string"
					},
					"sourcefile": {
						"type": "string"
					},
					"sinkcontainer": {
						"type": "string"
					},
					"sinkdirectory": {
						"type": "string"
					},
					"sinkfile": {
						"type": "string"
					},
					"url": {
						"type": "string"
					}
				},
				"variables": {
					"url": {
						"type": "String"
					}
				},
				"annotations": [],
				"lastPublishTime": "2025-02-19T14:01:35Z"
			},
			"dependsOn": [
				"[concat(variables('factoryId'), '/datasets/adlsparamdataset')]"
			]
		},
		{
			"name": "[concat(parameters('factoryName'), '/pipelineifelse')]",
			"type": "Microsoft.DataFactory/factories/pipelines",
			"apiVersion": "2018-06-01",
			"properties": {
				"activities": [
					{
						"name": "Get Metadata1",
						"type": "GetMetadata",
						"dependsOn": [],
						"policy": {
							"timeout": "0.12:00:00",
							"retry": 0,
							"retryIntervalInSeconds": 30,
							"secureOutput": false,
							"secureInput": false
						},
						"userProperties": [],
						"typeProperties": {
							"dataset": {
								"referenceName": "adlsmetadata",
								"type": "DatasetReference",
								"parameters": {}
							},
							"fieldList": [
								"childItems"
							],
							"storeSettings": {
								"type": "AzureBlobFSReadSettings",
								"recursive": true,
								"enablePartitionDiscovery": false
							},
							"formatSettings": {
								"type": "DelimitedTextReadSettings"
							}
						}
					},
					{
						"name": "ForEach1",
						"type": "ForEach",
						"dependsOn": [
							{
								"activity": "Get Metadata1",
								"dependencyConditions": [
									"Succeeded"
								]
							}
						],
						"userProperties": [],
						"typeProperties": {
							"items": {
								"value": "@activity('Get Metadata1').output.childItems",
								"type": "Expression"
							},
							"isSequential": true,
							"activities": [
								{
									"name": "Set variable1",
									"type": "SetVariable",
									"dependsOn": [],
									"policy": {
										"secureOutput": false,
										"secureInput": false
									},
									"userProperties": [],
									"typeProperties": {
										"variableName": "str",
										"value": {
											"value": "@item().type",
											"type": "Expression"
										}
									}
								},
								{
									"name": "If Condition1",
									"type": "IfCondition",
									"dependsOn": [
										{
											"activity": "Set variable1",
											"dependencyConditions": [
												"Succeeded"
											]
										}
									],
									"userProperties": [],
									"typeProperties": {
										"expression": {
											"value": "@equals(item().type,'Folder' )",
											"type": "Expression"
										},
										"ifTrueActivities": [
											{
												"name": "Copy data1",
												"type": "Copy",
												"dependsOn": [],
												"policy": {
													"timeout": "0.12:00:00",
													"retry": 0,
													"retryIntervalInSeconds": 30,
													"secureOutput": false,
													"secureInput": false
												},
												"userProperties": [],
												"typeProperties": {
													"source": {
														"type": "DelimitedTextSource",
														"storeSettings": {
															"type": "AzureBlobFSReadSettings",
															"recursive": true,
															"enablePartitionDiscovery": false
														},
														"formatSettings": {
															"type": "DelimitedTextReadSettings"
														}
													},
													"sink": {
														"type": "DelimitedTextSink",
														"storeSettings": {
															"type": "AzureBlobStorageWriteSettings"
														},
														"formatSettings": {
															"type": "DelimitedTextWriteSettings",
															"quoteAllText": true,
															"fileExtension": ".txt"
														}
													},
													"enableStaging": false,
													"translator": {
														"type": "TabularTranslator",
														"typeConversion": true,
														"typeConversionSettings": {
															"allowDataTruncation": true,
															"treatBooleanAsNumber": false
														}
													}
												},
												"inputs": [
													{
														"referenceName": "adlstoblbmeta",
														"type": "DatasetReference",
														"parameters": {
															"filename": {
																"value": "@item().name",
																"type": "Expression"
															}
														}
													}
												],
												"outputs": [
													{
														"referenceName": "blbmeta",
														"type": "DatasetReference",
														"parameters": {
															"destfilename": {
																"value": "@item().name",
																"type": "Expression"
															}
														}
													}
												]
											}
										]
									}
								}
							]
						}
					}
				],
				"policy": {
					"elapsedTimeMetric": {}
				},
				"variables": {
					"str": {
						"type": "String"
					},
					"i": {
						"type": "Integer"
					},
					"j": {
						"type": "Integer"
					}
				},
				"annotations": [],
				"lastPublishTime": "2025-02-18T12:24:00Z"
			},
			"dependsOn": [
				"[concat(variables('factoryId'), '/datasets/adlstoblbmeta')]",
				"[concat(variables('factoryId'), '/datasets/blbmeta')]"
			]
		}
	]
}